skcredit/__init__.py
skcredit/feature_selector/BaseSelect.py
skcredit/feature_selector/SelectBINS.py
skcredit/feature_selector/SelectCMIM.py
skcredit/feature_selector/__init__.py
skcredit/feature_spliters/CXSpliters.py
skcredit/feature_spliters/SplitMixND.py
skcredit/feature_spliters/WoEEncoder.py
skcredit/feature_spliters/__init__.py
skcredit/linear_model/LMClassifier.py
skcredit/linear_model/LMCreditcard.py
skcredit/linear_model/__init__.py
skcredit/tools/__init__.py
skcredit/tools/bucketer_tools.py
skcredit/tools/selector_tools.py
skcredit-0.0.5.dist-info/LICENSE
skcredit-0.0.5.dist-info/METADATA
skcredit-0.0.5.dist-info/WHEEL
skcredit-0.0.5.dist-info/top_level.txt
skcredit-0.0.5.dist-info/RECORD
