Metadata-Version: 2.1
Name: skcredit
Version: 0.0.5
Summary: scorecard
Home-page: https://github.com/JYLFamily/scikit-credit
Author: JYLFamily
Author-email: jiangyilanf@gmail.com
License: UNKNOWN
Platform: UNKNOWN
Classifier: Programming Language :: Python :: 3.7
Classifier: Programming Language :: Python :: 3.8
Classifier: Programming Language :: Python :: 3.9
Classifier: Programming Language :: Python :: 3.10
Classifier: Operating System :: OS Independent
Classifier: License :: OSI Approved :: GNU General Public License v3 (GPLv3)
License-File: LICENSE
Requires-Dist: numpy
Requires-Dist: altair
Requires-Dist: joblib
Requires-Dist: pandas
Requires-Dist: portion
Requires-Dist: statsmodels
Requires-Dist: scikit-learn
